holoconf/__init__.py
holoconf/__main__.py
holoconf/_holoconf.abi3.so
holoconf/_holoconf.pyi
holoconf/cli.py
holoconf/py.typed
holoconf-0.4.0.dist-info/METADATA
holoconf-0.4.0.dist-info/WHEEL
holoconf-0.4.0.dist-info/entry_points.txt
holoconf.libs/libgcc_s-6d2d9dc8.so.1
holoconf-0.4.0.dist-info/RECORD
