Metadata-Version: 2.4
Name: holoconf
Version: 0.4.0
Classifier: Development Status :: 3 - Alpha
Classifier: Intended Audience :: Developers
Classifier: License :: OSI Approved :: MIT License
Classifier: License :: OSI Approved :: Apache Software License
Classifier: Programming Language :: Python :: 3
Classifier: Programming Language :: Python :: 3.8
Classifier: Programming Language :: Python :: 3.9
Classifier: Programming Language :: Python :: 3.10
Classifier: Programming Language :: Python :: 3.11
Classifier: Programming Language :: Python :: 3.12
Classifier: Programming Language :: Python :: 3.13
Classifier: Programming Language :: Python :: Implementation :: CPython
Classifier: Programming Language :: Rust
Classifier: Topic :: Software Development :: Libraries :: Python Modules
Requires-Dist: maturin>=1.0,<2.0 ; extra == 'dev'
Requires-Dist: pytest>=7.0 ; extra == 'dev'
Requires-Dist: pytest-cov>=4.0 ; extra == 'dev'
Requires-Dist: pyyaml>=6.0 ; extra == 'dev'
Requires-Dist: ruff>=0.8 ; extra == 'dev'
Requires-Dist: pip-audit>=2.7 ; extra == 'dev'
Requires-Dist: cyclonedx-bom>=4.0 ; extra == 'dev'
Provides-Extra: dev
Summary: Cross-language configuration library with resolver support
Keywords: config,configuration,yaml,resolver
Author-email: Ryan <ryan@example.com>
License: MIT OR Apache-2.0
Requires-Python: >=3.8
Project-URL: Changelog, https://github.com/rfestag/holoconf/blob/main/CHANGELOG.md
Project-URL: Documentation, https://rfestag.github.io/holoconf/
Project-URL: Homepage, https://rfestag.github.io/holoconf/
Project-URL: Repository, https://github.com/rfestag/holoconf
